jupyterlab_training/__init__.py
jupyterlab_training/_version.py
jupyterlab_training-0.8.3.data/data/etc/jupyter/jupyter_server_config.d/jupyterlab-training.json
jupyterlab_training-0.8.3.data/data/share/jupyter/labextensions/jupyterlab-training/package.json
jupyterlab_training-0.8.3.data/data/share/jupyter/labextensions/jupyterlab-training/schemas/jupyterlab-training/package.json.orig
jupyterlab_training-0.8.3.data/data/share/jupyter/labextensions/jupyterlab-training/static/210.56dda83aac8ec0617111.js
jupyterlab_training-0.8.3.data/data/share/jupyter/labextensions/jupyterlab-training/static/365.f15319010251439d7f03.js
jupyterlab_training-0.8.3.data/data/share/jupyter/labextensions/jupyterlab-training/static/526.42e13434ed736f82e1f5.js
jupyterlab_training-0.8.3.data/data/share/jupyter/labextensions/jupyterlab-training/static/728.55ec945f87c9e67c5650.js
jupyterlab_training-0.8.3.data/data/share/jupyter/labextensions/jupyterlab-training/static/793.ada6f0094fa171ff194e.js
jupyterlab_training-0.8.3.data/data/share/jupyter/labextensions/jupyterlab-training/static/908.df6b5f76d9f53b1162fd.js
jupyterlab_training-0.8.3.data/data/share/jupyter/labextensions/jupyterlab-training/static/9c539cf459fdeaebf683.png
jupyterlab_training-0.8.3.data/data/share/jupyter/labextensions/jupyterlab-training/static/remoteEntry.b3ad3428617b39a42a99.js
jupyterlab_training-0.8.3.data/data/share/jupyter/labextensions/jupyterlab-training/static/style.js
jupyterlab_training-0.8.3.data/data/share/jupyter/labextensions/jupyterlab-training/static/third-party-licenses.json
jupyterlab_training-0.8.3.data/data/share/jupyter/labextensions/jupyterlab-training/install.json
jupyterlab_training-0.8.3.dist-info/METADATA
jupyterlab_training-0.8.3.dist-info/WHEEL
jupyterlab_training-0.8.3.dist-info/licenses/LICENSE
jupyterlab_training-0.8.3.dist-info/RECORD
