Metadata-Version: 2.1
Name: jupyterlab_training
Version: 0.8.3
Summary: jupyterlab training courses and exercices platform.
Author-email: Logilab <ogiorgis@logilab.fr>
License: BSD 3-Clause License
License-File: LICENSE
Classifier: Framework :: Jupyter
Classifier: Framework :: Jupyter :: JupyterLab
Classifier: Framework :: Jupyter :: JupyterLab :: 4
Classifier: Framework :: Jupyter :: JupyterLab :: Extensions
Classifier: Framework :: Jupyter :: JupyterLab :: Extensions :: Prebuilt
Classifier: License :: OSI Approved :: BSD License
Classifier: Programming Language :: Python
Classifier: Programming Language :: Python :: 3
Classifier: Programming Language :: Python :: 3.8
Classifier: Programming Language :: Python :: 3.9
Classifier: Programming Language :: Python :: 3.10
Classifier: Programming Language :: Python :: 3.11
Requires-Python: >=3.9
Requires-Dist: arrow
Requires-Dist: flake8
Requires-Dist: ipython-unittest
Requires-Dist: ipywidgets
Requires-Dist: jsonschema
Requires-Dist: jupyterlab-tour
Requires-Dist: jupyterquiz
Requires-Dist: pygments
Requires-Dist: sqlalchemy
Requires-Dist: sqlalchemy-utils
